maestro_cubes/__init__.py
maestro_cubes-0.0.1.dist-info/METADATA
maestro_cubes-0.0.1.dist-info/WHEEL
maestro_cubes-0.0.1.dist-info/RECORD
