Metadata-Version: 2.4
Name: maestro-cubes
Version: 0.0.1
Summary: YAML-driven modular pipeline orchestrator for document-to-audio transformation. Coming soon.
Project-URL: Homepage, https://github.com/muid-io/maestro-cubes
Project-URL: Documentation, https://github.com/muid-io/maestro-cubes
Author-email: "Muid.io" <dev@muid.io>
License: MIT
Keywords: ai,audio,cubes,orchestration,pipeline,tts,yaml
Classifier: Development Status :: 1 - Planning
Classifier: Intended Audience :: Developers
Classifier: License :: OSI Approved :: MIT License
Classifier: Programming Language :: Python :: 3
Classifier: Programming Language :: Python :: 3.10
Classifier: Programming Language :: Python :: 3.11
Classifier: Programming Language :: Python :: 3.12
Classifier: Topic :: Software Development :: Libraries :: Python Modules
Requires-Python: >=3.10
